Datum/__init__.py
robotframework_Datum-1.1.1.dist-info/LICENSE.txt
robotframework_Datum-1.1.1.dist-info/METADATA
robotframework_Datum-1.1.1.dist-info/WHEEL
robotframework_Datum-1.1.1.dist-info/top_level.txt
robotframework_Datum-1.1.1.dist-info/RECORD
