Metadata-Version: 2.1
Name: robotframework-Datum
Version: 1.1.1
Summary: robot framework library that contains a set of functions for working with JSON, PDf and Text..
Home-page: https://github.com/hassineabd/robotframeworkdatum
Author: Abdelkader HASSINE;           Rafik SAADA
Author-email: contact.abdelkaderhassine@gmail.com
Classifier: Topic :: Software Development :: Testing
Classifier: License :: OSI Approved :: GNU General Public License v3 (GPLv3)
Classifier: Programming Language :: Python :: 3.6
Classifier: Programming Language :: Python :: 3.7
Classifier: Programming Language :: Python :: 3.8
Classifier: Programming Language :: Python :: 3.9
Classifier: Operating System :: OS Independent
Requires-Python: >=3.0
License-File: LICENSE.txt
Requires-Dist: PyPDF2
